nova_server/__init__.py
nova_server/app.py
nova_server/backend/__init__.py
nova_server/backend/virtual_environment.py
nova_server/data/__init__.py
nova_server/data/adjectives.py
nova_server/data/animals.py
nova_server/data/colors.py
nova_server/data/countries.py
nova_server/data/languages.py
nova_server/data/names.py
nova_server/data/star_wars.py
nova_server/exec/__init__.py
nova_server/exec/ex_extract.py
nova_server/exec/ex_predict.py
nova_server/exec/ex_train.py
nova_server/exec/execution_handler.py
nova_server/route/__init__.py
nova_server/route/cancel.py
nova_server/route/deprecated_extract.py
nova_server/route/deprecated_train.py
nova_server/route/explain.py
nova_server/route/extract.py
nova_server/route/log.py
nova_server/route/predict.py
nova_server/route/status.py
nova_server/route/train.py
nova_server/route/ui.py
nova_server/templates/__init__.py
nova_server/utils/__init__.py
nova_server/utils/deprecated_dataset_utils.py
nova_server/utils/deprecated_db_utils.py
nova_server/utils/deprecated_explain_utils.py
nova_server/utils/env.py
nova_server/utils/import_utils.py
nova_server/utils/job_utils.py
nova_server/utils/log_utils.py
nova_server/utils/thread_utils.py
nova_server/utils/venv_utils.py
hcai_nova_server_nightly-0.1.15.dev202309131500.dist-info/METADATA
hcai_nova_server_nightly-0.1.15.dev202309131500.dist-info/WHEEL
hcai_nova_server_nightly-0.1.15.dev202309131500.dist-info/entry_points.txt
hcai_nova_server_nightly-0.1.15.dev202309131500.dist-info/top_level.txt
hcai_nova_server_nightly-0.1.15.dev202309131500.dist-info/RECORD
